nsj_queue_lib/__init__.py
nsj_queue_lib/db_gen.py
nsj_queue_lib/queue_client.py
nsj_queue_lib/settings.py
nsj_queue_lib/worker_base.py
nsj_queue_lib/worker_fila_teste.py
nsj_queue_lib/worker_pub_sub_base.py
nsj_queue_lib/worker_pub_sub_teste.py
nsj_queue_lib/worker_webhook.py
nsj_queue_lib/client/__init__.py
nsj_queue_lib/client/exception.py
nsj_queue_lib/client/lock_client.py
nsj_queue_lib/client/main_thread.py
nsj_queue_lib/client/multidabase_client.py
nsj_queue_lib/client/notify_thread.py
nsj_queue_lib/client/purge_thread.py
nsj_queue_lib/client/retry_thread.py
nsj_queue_lib/client/retry_util.py
nsj_queue_lib/client/socket_client.py
nsj_queue_lib/client/socket_connection.py
nsj_queue_lib/client/tarefa_dao.py
nsj_queue_lib/server/__init__.py
nsj_queue_lib/server/check_tasks_thread.py
nsj_queue_lib/server/listener_thread.py
nsj_queue_lib/server/lock_service.py
nsj_queue_lib/server/lock_service_thread.py
nsj_queue_lib/server/rpc_interpreter.py
nsj_queue_lib/server/server_main.py
nsj_queue_lib/server/server_settings.py
nsj_queue_lib/server/socket_io.py
nsj_queue_lib-1.2.2.dist-info/METADATA
nsj_queue_lib-1.2.2.dist-info/WHEEL
nsj_queue_lib-1.2.2.dist-info/top_level.txt
nsj_queue_lib-1.2.2.dist-info/RECORD
