Metadata-Version: 2.4
Name: nsj_queue_lib
Version: 1.2.2
Summary: Biblioteca para facilitar a implementação de filas e workers.
Home-page: https://github.com/Nasajon/nsj-queue-lib
Author: Nasajon Sistemas
Author-email: contact.dev@nasajon.com.br
Project-URL: Source, https://github.com/Nasajon/nsj-queue-lib
Classifier: Development Status :: 3 - Alpha
Classifier: Intended Audience :: Developers
Classifier: Topic :: Software Development :: Libraries
Classifier: Programming Language :: Python :: 3
Requires-Python: >=3.4
Requires-Dist: psycopg2_binary<3.0.0,>=2.9.6
Requires-Dist: python-logging-loki<1.0.0,>=0.3.1
Requires-Dist: pytest<8.0.0,>=7.1.3
Requires-Dist: nsj_sql_utils_lib<3.0.0,>=2.0.0
Requires-Dist: nsj_gcf_utils<2.0.0,>=1.0.14
